README
setup.py
python_slimtimer.egg-info/PKG-INFO
python_slimtimer.egg-info/SOURCES.txt
python_slimtimer.egg-info/dependency_links.txt
python_slimtimer.egg-info/requires.txt
python_slimtimer.egg-info/top_level.txt
python_slimtimer.egg-info/zip-safe
slimtimer/__init__.py
slimtimer/api.py