Metadata-Version: 1.0
Name: python-slimtimer
Version: 0.1.0
Summary: SlimTimer interface for Python
Home-page: http://github.com/eugeneoden/python-slimtimer
Author: Eugene Oden
Author-email: eugeneoden@gmail.com
License: BSD
Keywords: slimtimer slim timer
Platform: UNKNOWN
